rmlab_errors/__init__.py
tests/__init__.py
tests/errors_test.py
rmlab_errors-0.1.6.dist-info/LICENSE
rmlab_errors-0.1.6.dist-info/METADATA
rmlab_errors-0.1.6.dist-info/WHEEL
rmlab_errors-0.1.6.dist-info/top_level.txt
rmlab_errors-0.1.6.dist-info/RECORD
