Metadata-Version: 2.1
Name: rmlab-errors
Version: 0.1.6
Summary: RMLab module for unified error handling
Home-page: https://github.com/antonrv/rmlab-py-errors
Author: Anton Rey
Author-email: aanton.rv@gmail.com
Project-URL: Bug Tracker, https://github.com/antonrv/rmlab-py-errors/issues
Classifier: License :: OSI Approved :: MIT License
Classifier: Development Status :: 4 - Beta
Classifier: Programming Language :: Python
Classifier: Programming Language :: Python :: 3.9
Classifier: Programming Language :: Python :: 3 :: Only
Classifier: Operating System :: OS Independent
Classifier: Environment :: Console
Classifier: Intended Audience :: Developers
Classifier: Topic :: Office/Business
Classifier: Topic :: Scientific/Engineering
Classifier: Topic :: Software Development :: User Interfaces
Requires-Python: >=3.9
License-File: LICENSE
